long_audio_whisper/__init__.py
long_audio_whisper/processor.py
long_audio_whisper-1.0.0.dist-info/licenses/LICENSE
long_audio_whisper-1.0.0.dist-info/METADATA
long_audio_whisper-1.0.0.dist-info/WHEEL
long_audio_whisper-1.0.0.dist-info/top_level.txt
long_audio_whisper-1.0.0.dist-info/RECORD
