Metadata-Version: 2.4
Name: long-audio-whisper
Version: 1.0.0
Summary: A library to bypass OpenAI Whisper's 25MB limit by chunking long audio files, with LLM-powered text enhancement and precise timestamp reconstruction for SRT/VTT formats.
Home-page: https://github.com/bokamix/long-audio-whisper
Author: bokamix
Author-email: wjaniak@jede.pl
License: MIT
Keywords: openai whisper transcription audio speech-to-text long-audio srt vtt
Classifier: Development Status :: 5 - Production/Stable
Classifier: Intended Audience :: Developers
Classifier: Topic :: Multimedia :: Sound/Audio :: Speech
Classifier: Topic :: Scientific/Engineering :: Artificial Intelligence
Classifier: Programming Language :: Python :: 3
Classifier: Programming Language :: Python :: 3.8
Classifier: Programming Language :: Python :: 3.9
Classifier: Programming Language :: Python :: 3.10
Classifier: Programming Language :: Python :: 3.11
Classifier: Operating System :: OS Independent
Requires-Python: >=3.8
License-File: LICENSE
Requires-Dist: openai
Requires-Dist: pydub
Requires-Dist: tenacity
Dynamic: author
Dynamic: author-email
Dynamic: classifier
Dynamic: description
Dynamic: description-content-type
Dynamic: home-page
Dynamic: keywords
Dynamic: license
Dynamic: license-file
Dynamic: requires-dist
Dynamic: requires-python
Dynamic: summary
